[{"pageContent":"Yes.","metadata":{"fillerID":21,"fillerText":"Yeah","category":"C"}},{"pageContent":"Well, I was scrolling through the YouTube okay. And Im trying to find a place where I can Im retired security, and thats not enough.","metadata":{"fillerID":9,"fillerText":"Interesting","category":"A"}},{"pageContent":"So I need to find some way of increasing my net worth.","metadata":{"fillerID":9,"fillerText":"Interesting","category":"A"}},{"pageContent":"All right. Have a good one, Bob. Bye.","metadata":{"fillerID":45,"fillerText":"Yeah","category":"G"}},{"pageContent":"About $800 a month.","metadata":{"fillerID":45,"fillerText":"Yeah","category":"G"}},{"pageContent":"All right. I appreciate that.","metadata":{"fillerID":22,"fillerText":"Okay","category":"C"}},{"pageContent":"Sounds good. All right.","metadata":{"fillerID":42,"fillerText":"Ok gotcha","category":"G"}},{"pageContent":"All right.","metadata":{"fillerID":43,"fillerText":"Ok yah","category":"G"}},{"pageContent":"Right.","metadata":{"fillerID":45,"fillerText":"Yeah","category":"G"}},{"pageContent":"Yes, I did.","metadata":{"fillerID":21,"fillerText":"Yeah","category":"C"}}]